main.py
what_is_my_ip_simp-0.1.3.dist-info/METADATA
what_is_my_ip_simp-0.1.3.dist-info/WHEEL
what_is_my_ip_simp-0.1.3.dist-info/entry_points.txt
what_is_my_ip_simp-0.1.3.dist-info/top_level.txt
what_is_my_ip_simp-0.1.3.dist-info/RECORD
