Metadata-Version: 2.4
Name: what-is-my-ip-simp
Version: 0.1.3
Summary: This module can help you to grab your public IP address
Requires-Python: >=3.14
Requires-Dist: beautifulsoup4>=4.14.3
Requires-Dist: html5lib>=1.1
Requires-Dist: requests>=2.32.5
